aws_sdk_signers/__init__.py
aws_sdk_signers/_http.py
aws_sdk_signers/_identity.py
aws_sdk_signers/_io.py
aws_sdk_signers/_version.py
aws_sdk_signers/exceptions.py
aws_sdk_signers/py.typed
aws_sdk_signers/signers.py
aws_sdk_signers/interfaces/__init__.py
aws_sdk_signers/interfaces/http.py
aws_sdk_signers/interfaces/identity.py
aws_sdk_signers/interfaces/io.py
aws_sdk_signers-0.0.2.dist-info/METADATA
aws_sdk_signers-0.0.2.dist-info/WHEEL
aws_sdk_signers-0.0.2.dist-info/licenses/LICENSE
aws_sdk_signers-0.0.2.dist-info/licenses/NOTICE
aws_sdk_signers-0.0.2.dist-info/RECORD
