Metadata-Version: 2.3
Name: aws-sdk-signers
Version: 0.0.2
Summary: Standalone HTTP Request Signers for Amazon Web Services
Author: Amazon Web Services
License: 
License-File: LICENSE
License-File: NOTICE
Keywords: AWS,HTTP,SigV4,Signing
Classifier: Development Status :: 2 - Pre-Alpha
Classifier: Programming Language :: Python
Classifier: Programming Language :: Python :: 3.12
Requires-Python: >=3.12
Provides-Extra: test
Requires-Dist: freezegun; extra == 'test'
Requires-Dist: mypy; extra == 'test'
Requires-Dist: pytest; extra == 'test'
Requires-Dist: pytest-asyncio; extra == 'test'
Requires-Dist: ruff; extra == 'test'
